{"S_down": 21.1, "maxvalue": 16.4, "range1": 23.6, "range2": 24.4, "dmq": 19.6, "V_sum": 17.2, "S_ret": 28.0, "curvature": 20.0, "alt_stderr_mean_5": 22.4, "alt_rvalue_min_50": 23.3, "V1": 24.8, "V2": 27.3, "stability": 24.3, "std": 24.3, "level_shift_size": 22.1, "var": 25.9, "dnp": 30.8, "fft_abs_1": 25.4, "F1": 15.2, "asoc": 18.7, "F2": 17.9, "erbc_num10_focus4": 30.0, "erbc_num10_focus2": 21.6, "maxindex": 12.2, "minang": 32.0, "fft_imag_3": 27.4, "fft_imag_6": 24.6, "fft_abs_22": 24.7, "lumpiness": 25.0, "minindex": 7.3, "alt_stderr_max_10": 30.9, "retvalue": 21.5, "sumang": 32.7, "mac": 34.9, "S": 37.1, "retang": 35.6, "S_low": 32.9, "retindex": 11.0, "S_sum": 31.2, "alt_stderr_min_5": 27.1, "minvalue": 30.1, "alt_stderr_mean_10": 33.9, "swd_coeff_2": 31.0, "std1st_der": 25.5, "cv": 24.8, "fft_angle_2": 25.9, "maxang": 38.3, "fft_real_2": 23.9, "fft_real_5": 21.0, "alt_stderr_min_50": 33.3, "alt_stderr_max_5": 34.8, "fft_angle_3": 31.1}